typer_config/__init__.py
typer_config/__optional_imports.py
typer_config/__typing.py
typer_config/callbacks.py
typer_config/decorators.py
typer_config/dumpers.py
typer_config/loaders.py
typer_config/py.typed
typer_config/utils.py
typer_config-1.4.2.dist-info/LICENSE
typer_config-1.4.2.dist-info/METADATA
typer_config-1.4.2.dist-info/WHEEL
typer_config-1.4.2.dist-info/RECORD
