Metadata-Version: 2.1
Name: typer-config
Version: 1.4.2
Summary: Utilities for working with configuration files in typer CLIs. 
Home-page: https://maxb2.github.io/typer-config/
License: MIT
Keywords: typer,config,configuration,configuration-file,yaml,toml,json,dotenv,cli
Author: Matt Anderson
Author-email: matt@manderscience.com
Requires-Python: >=3.9,<4.0
Classifier: Intended Audience :: Developers
Classifier: Intended Audience :: Information Technology
Classifier: Intended Audience :: System Administrators
Classifier: License :: OSI Approved :: MIT License
Classifier: Operating System :: OS Independent
Classifier: Programming Language :: Python
Classifier: Programming Language :: Python :: 3
Classifier: Programming Language :: Python :: 3.9
Classifier: Programming Language :: Python :: 3.10
Classifier: Programming Language :: Python :: 3.11
Classifier: Programming Language :: Python :: 3.12
Classifier: Programming Language :: Python :: 3.13
Classifier: Programming Language :: Python :: 3 :: Only
Classifier: Programming Language :: Python :: 3.8
Classifier: Topic :: Software Development
Classifier: Topic :: Software Development :: Libraries
Classifier: Topic :: Software Development :: Libraries :: Application Frameworks
Classifier: Topic :: Software Development :: Libraries :: Python Modules
Classifier: Typing :: Typed
Provides-Extra: all
Provides-Extra: python-dotenv
Provides-Extra: toml
Provides-Extra: yaml
Requires-Dist: python-dotenv ; extra == "python-dotenv" or extra == "all"
Requires-Dist: pyyaml (>=6.0,<7.0) ; extra == "yaml" or extra == "all"
Requires-Dist: toml (>=0.10.2,<0.11.0) ; extra == "toml" or extra == "all"
Requires-Dist: typer (>=0,<1)
Project-URL: Documentation, https://maxb2.github.io/typer-config/
Project-URL: Repository, https://github.com/maxb2/typer-config
